[{"value": "&country=us", "label": "United States"}, {"value": "&country=gb", "label": "Great Britain"}, {"value": "&country=de", "label": "Germany"}, 
{"value": "&country=it", "label": "Italy"}, {"value": "&country=fr", "label": "France"}, {"value": "&country=ca", "label": "Canada"}, 
{"value": "&country=nl", "label": "Netherlands"}, {"value": "&country=se", "label": "Sweden"}, {"value": "&country=dk", "label": "Denmark"}, 
{"value": "&country=fi", "label": "Finland"}, {"value": "&country=hu", "label": "Hungary"}, {"value": "&country=no", "label": "Norway"},
{"value": "&country=pl", "label": "Poland"}, {"value": "&country=pt", "label": "Portugal"}, {"value": "&country=ru", "label": "Russia"}, 
{"value": "&country=ua", "label": "Ukraine"}, {"value": "&country=ch", "label": "Switzerland"}, {"value": "&country=br", "label": "Brazil"}, 
{"value": "&country=nz", "label": "New Zealand"}, {"value": "&country=mx", "label": "Mexico"}, {"value": "&country=au", "label": "Australia"},
{"value": "&country=in", "label": "India"}]